README.md
setup.cfg
setup.py
tornado_redis_session/__init__.py
tornado_redis_session/session.py
tornado_redis_session.egg-info/PKG-INFO
tornado_redis_session.egg-info/SOURCES.txt
tornado_redis_session.egg-info/dependency_links.txt
tornado_redis_session.egg-info/requires.txt
tornado_redis_session.egg-info/top_level.txt