Metadata-Version: 1.0
Name: tornado-redis-session
Version: 0.1.3
Summary: Server side session middleware based on redis
Home-page: https://github.com/hw20686832/tornado-redis-session
Author: David Wong
Author-email: stef-hw@163.com
License: UNKNOWN
Keywords: tornado,session,redis
Platform: UNKNOWN
